rdfpy/__init__.py
rdfpy/rdfpy.py
tests/__init__.py
tests/test_rdf.py
rdfpy-1.0.0.dist-info/LICENSE
rdfpy-1.0.0.dist-info/METADATA
rdfpy-1.0.0.dist-info/WHEEL
rdfpy-1.0.0.dist-info/top_level.txt
rdfpy-1.0.0.dist-info/RECORD
