Metadata-Version: 2.1
Name: rdfpy
Version: 1.0.0
Summary: rdfpy is a Python package for computing 2D and 3D radial distribution functions.
Home-page: https://github.com/by256/rdfpy
Author: Batuhan Yildirim
Author-email: by256@cam.ac.uk
License: MIT
Platform: UNKNOWN
Classifier: Programming Language :: Python :: 3
Classifier: License :: OSI Approved :: MIT License
Classifier: Operating System :: OS Independent
Requires-Dist: scipy
Requires-Dist: numpy
Requires-Dist: matplotlib
